{
  "date": "2023-12-05",
  "scenario": "eshop-on-blazor-modified-rebuild-dotnet",
  "timestamp": "2023-12-05T11:59:50.0260228Z",
  "perfstarCIBuildNumber": "20231205.2",
  "branch": "refs/heads/main",
  "ciRunReason": "Schedule",
  "schemaVersion": "2",
  "results": {
    "netSdkVersion": "7.0.404",
    "aspNetCoreVersion": "7.0.14+0a715692d8e2",
    "netCoreAppVersion": "7.0.14+808851b07acf",
    "msbuild-version": "17.9.0.60502",
    "msbuild-display-version": "MSBuild version 17.9.0-preview-23605-02+2f3d37672 for .NET",
    "evaluation-time-first": 445.0,
    "evaluation-time-globbing-first": 8.0,
    "evaluation-time-pass0-first": 6.0,
    "evaluation-time-pass1-first": 236.0,
    "evaluation-time-pass2-first": 1.0,
    "evaluation-time-pass3-first": 37.0,
    "evaluation-time-pass3dot1-first": 96.0,
    "evaluation-time-pass4-first": 4.0,
    "evaluation-time-pass5-first": 63.0,
    "evaluation-time": 451.0,
    "evaluation-time-globbing": 7.0,
    "evaluation-time-pass0": 6.0,
    "evaluation-time-pass1": 244.0,
    "evaluation-time-pass2": 1.0,
    "evaluation-time-pass3": 37.0,
    "evaluation-time-pass3dot1": 95.0,
    "evaluation-time-pass4": 4.0,
    "evaluation-time-pass5": 62.0,
    "build-time": 1990.9996,
    "exit-code": 0.0,
    "info/test-asset": "eShopOnBlazor-modified",
    "info/test-scenario": "Rebuild",
    "info/msbuild-app": "Dotnet",
    "info/test-version": 0.0,
    "dotnet-version": "9.0.100-alpha.1.23604.8"
  }
}
