{
  "date": "2024-03-26",
  "scenario": "csproj-web-app-inc-build-msbuild",
  "perfstarCIBuildNumber": "20240326.1",
  "branch": "refs/heads/perf/AR-May/build-analyzers-on",
  "ciRunReason": "Manual",
  "schemaVersion": "2",
  "results": {
    "netSdkVersion": "7.0.407",
    "aspNetCoreVersion": "7.0.17+d0ca5a8d20ac",
    "netCoreAppVersion": "7.0.17+dff486f2d78d",
    "msbuild-version": "17.10.0.17203",
    "msbuild-display-version": "MSBuild version 17.10.0-preview-24172-03+c20064ea7 for .NET Framework",
    "evaluation-time-first": 372.0,
    "evaluation-time-globbing-first": 0.0,
    "evaluation-time-pass0-first": 7.0,
    "evaluation-time-pass1-first": 169.0,
    "evaluation-time-pass2-first": 2.0,
    "evaluation-time-pass3-first": 44.0,
    "evaluation-time-pass3dot1-first": 86.0,
    "evaluation-time-pass4-first": 11.0,
    "evaluation-time-pass5-first": 48.0,
    "evaluation-time": 372.0,
    "evaluation-time-globbing": 0.0,
    "evaluation-time-pass0": 7.0,
    "evaluation-time-pass1": 170.0,
    "evaluation-time-pass2": 2.0,
    "evaluation-time-pass3": 44.0,
    "evaluation-time-pass3dot1": 87.0,
    "evaluation-time-pass4": 11.0,
    "evaluation-time-pass5": 48.0,
    "build-time": 1528.7917,
    "exit-code": 0.0,
    "info/test-asset": "CSProjWebApplication",
    "info/test-scenario": "IncrementalBuild",
    "info/msbuild-app": "MSBuild",
    "info/test-version": 0.0
  }
}
