{
  "date": "2025-06-25",
  "scenario": "net6-console-app-inc-build-dotnet",
  "perfstarCIBuildNumber": "20250625.1.s",
  "branch": "refs/heads/main",
  "ciRunReason": "Schedule",
  "schemaVersion": "2",
  "results": {
    "netSdkVersion": "8.0.411",
    "aspNetCoreVersion": "8.0.17+fa4d80b76c24",
    "netCoreAppVersion": "8.0.17+77545d6fd5ca",
    "msbuild-version": "17.15.0.32504",
    "msbuild-display-version": "17.15.0.32504",
    "evaluation-time": 494.1,
    "evaluation-time-globbing": 6.0,
    "evaluation-time-pass0": 6.0,
    "evaluation-time-pass1": 275.3,
    "evaluation-time-pass2": 2.0,
    "evaluation-time-pass3": 50.5,
    "evaluation-time-pass3dot1": 46.4,
    "evaluation-time-pass4": 3.7,
    "evaluation-time-pass5": 108.2,
    "exit-code": 0.0,
    "build-time": 1273.08873,
    "info/test-asset": "Net6ConsoleApp",
    "info/test-scenario": "IncrementalBuild",
    "info/msbuild-app": "Dotnet",
    "info/test-version": 1.0,
    "info/iterations-number": 10.0,
    "dotnet-version": "9.0.200"
  }
}
