{
  "date": "2024-02-24",
  "scenario": "net6-class-lib-inc-build-dotnet",
  "perfstarCIBuildNumber": "20240224.1",
  "branch": "refs/heads/main",
  "ciRunReason": "Unspecified",
  "schemaVersion": "2",
  "results": {
    "netSdkVersion": "7.0.406",
    "aspNetCoreVersion": "7.0.16+610fe433e07b",
    "netCoreAppVersion": "7.0.16+567edafe6106",
    "msbuild-version": "17.10.0.12301",
    "msbuild-display-version": "17.10.0.12301",
    "evaluation-time-first": 378.0,
    "evaluation-time-globbing-first": 5.0,
    "evaluation-time-pass0-first": 8.0,
    "evaluation-time-pass1-first": 198.0,
    "evaluation-time-pass2-first": 2.0,
    "evaluation-time-pass3-first": 49.0,
    "evaluation-time-pass3dot1-first": 46.0,
    "evaluation-time-pass4-first": 4.0,
    "evaluation-time-pass5-first": 70.0,
    "evaluation-time": 399.0,
    "evaluation-time-globbing": 5.0,
    "evaluation-time-pass0": 8.0,
    "evaluation-time-pass1": 218.0,
    "evaluation-time-pass2": 2.0,
    "evaluation-time-pass3": 49.0,
    "evaluation-time-pass3dot1": 46.0,
    "evaluation-time-pass4": 4.0,
    "evaluation-time-pass5": 70.0,
    "build-time": 1172.7204,
    "exit-code": 0.0,
    "info/test-asset": "Net6ClassLib",
    "info/test-scenario": "IncrementalBuild",
    "info/msbuild-app": "Dotnet",
    "info/test-version": 0.0,
    "dotnet-version": "9.0.100-preview.3.24123.6"
  }
}
