{
  "date": "2025-10-21",
  "scenario": "net6-console-app-rebuild-dotnet",
  "perfstarCIBuildNumber": "20251021.3.s",
  "branch": "refs/heads/main",
  "ciRunReason": "Schedule",
  "machineID": "PERFLIN",
  "schemaVersion": "2",
  "results": {
    "netSdkVersion": "10.0.100-rtm.25513.102",
    "aspNetCoreVersion": "10.0.0-rtm.25513.102+b502b6eeec0d",
    "netCoreAppVersion": "10.0.0-rtm.25513.102+b502b6eeec0d",
    "msbuild-version": "18.1.0.52103",
    "msbuild-display-version": "18.1.0.52103",
    "evaluation-time": 486.6,
    "evaluation-time-globbing": 2.0,
    "evaluation-time-pass0": 34.9,
    "evaluation-time-pass1": 254.2,
    "evaluation-time-pass2": 2.0,
    "evaluation-time-pass3": 48.6,
    "evaluation-time-pass3dot1": 48.6,
    "evaluation-time-pass4": 16.6,
    "evaluation-time-pass5": 79.2,
    "exit-code": 0.0,
    "build-time": 1295.9479100000003,
    "info/test-asset": "Net6ConsoleApp",
    "info/test-scenario": "Rebuild",
    "info/msbuild-app": "Dotnet",
    "info/test-version": 1.0,
    "info/iterations-number": 10.0,
    "dotnet-version": "10.0.100"
  }
}
