{
  "date": "2024-10-09",
  "scenario": "net8-console-app-inc-build-dotnet",
  "perfstarCIBuildNumber": "20241009.3",
  "branch": "refs/heads/main",
  "ciRunReason": "Unspecified",
  "schemaVersion": "2",
  "results": {
    "netSdkVersion": "8.0.403",
    "aspNetCoreVersion": "8.0.10+c2a442982e73",
    "netCoreAppVersion": "8.0.10+81cabf2857a0",
    "msbuild-version": "17.13.0.50908",
    "msbuild-display-version": "17.13.0.50908",
    "evaluation-time-first": 476.0,
    "evaluation-time-globbing-first": 5.0,
    "evaluation-time-pass0-first": 36.0,
    "evaluation-time-pass1-first": 243.0,
    "evaluation-time-pass2-first": 2.0,
    "evaluation-time-pass3-first": 49.0,
    "evaluation-time-pass3dot1-first": 58.0,
    "evaluation-time-pass4-first": 6.0,
    "evaluation-time-pass5-first": 79.0,
    "evaluation-time": 487.0,
    "evaluation-time-globbing": 6.0,
    "evaluation-time-pass0": 46.0,
    "evaluation-time-pass1": 244.0,
    "evaluation-time-pass2": 2.0,
    "evaluation-time-pass3": 49.0,
    "evaluation-time-pass3dot1": 58.0,
    "evaluation-time-pass4": 6.0,
    "evaluation-time-pass5": 80.0,
    "build-time": 1311.0311,
    "exit-code": 0.0,
    "info/test-asset": "Net8ConsoleApp",
    "info/test-scenario": "IncrementalBuild",
    "info/msbuild-app": "Dotnet",
    "info/test-version": 0.0,
    "dotnet-version": "9.0.200-preview.0.24508.47"
  }
}
