{
  "date": "2025-03-29",
  "scenario": "net8-console-app-rebuild-dotnet",
  "perfstarCIBuildNumber": "20250329.1.s",
  "branch": "refs/heads/main",
  "ciRunReason": "Schedule",
  "schemaVersion": "2",
  "results": {
    "netSdkVersion": "8.0.407",
    "aspNetCoreVersion": "8.0.14+25ef4aa38b77",
    "netCoreAppVersion": "8.0.14+1584e493603c",
    "msbuild-version": "17.15.0.17816",
    "msbuild-display-version": "17.15.0.17816",
    "evaluation-time": 497.4,
    "evaluation-time-globbing": 6.0,
    "evaluation-time-pass0": 6.2,
    "evaluation-time-pass1": 283.3,
    "evaluation-time-pass2": 2.0,
    "evaluation-time-pass3": 47.6,
    "evaluation-time-pass3dot1": 43.3,
    "evaluation-time-pass4": 3.4,
    "evaluation-time-pass5": 108.9,
    "exit-code": 0.0,
    "build-time": 1317.21934,
    "info/test-asset": "Net8ConsoleApp",
    "info/test-scenario": "Rebuild",
    "info/msbuild-app": "Dotnet",
    "info/test-version": 1.0,
    "info/iterations-number": 10.0,
    "dotnet-version": "9.0.200"
  }
}
