{
  "date": "2024-01-09",
  "scenario": "net8-wpf-app-rebuild-dotnet",
  "perfstarCIBuildNumber": "20240109.1",
  "branch": "refs/heads/perf/forgind/buildincludeoperation-optimizations",
  "ciRunReason": "ResourceTrigger",
  "schemaVersion": "2",
  "results": {
    "netSdkVersion": "7.0.405",
    "aspNetCoreVersion": "7.0.15+c49ccc8727c6",
    "netCoreAppVersion": "7.0.15+8f4568cdaa2f",
    "msbuild-version": "17.10.0.5902",
    "msbuild-display-version": "MSBuild version 17.10.0-preview-24059-02+51f3ded12 for .NET",
    "evaluation-time-first": 482.0,
    "evaluation-time-globbing-first": 6.0,
    "evaluation-time-pass0-first": 5.0,
    "evaluation-time-pass1-first": 247.0,
    "evaluation-time-pass2-first": 2.0,
    "evaluation-time-pass3-first": 59.0,
    "evaluation-time-pass3dot1-first": 62.0,
    "evaluation-time-pass4-first": 4.0,
    "evaluation-time-pass5-first": 100.0,
    "evaluation-time": 488.0,
    "evaluation-time-globbing": 6.0,
    "evaluation-time-pass0": 5.0,
    "evaluation-time-pass1": 248.0,
    "evaluation-time-pass2": 2.0,
    "evaluation-time-pass3": 61.0,
    "evaluation-time-pass3dot1": 60.0,
    "evaluation-time-pass4": 4.0,
    "evaluation-time-pass5": 105.0,
    "build-time": 1506.7813,
    "exit-code": 0.0,
    "info/test-asset": "Net8WpfApp",
    "info/test-scenario": "Rebuild",
    "info/msbuild-app": "Dotnet",
    "info/test-version": 0.0,
    "dotnet-version": "9.0.100-alpha.1.24059.8"
  }
}
