{
  "date": "2025-08-23",
  "scenario": "net8-blazorwasm-app-rebuild-binlog-dotnet",
  "perfstarCIBuildNumber": "20250823.1.s",
  "branch": "refs/heads/main",
  "ciRunReason": "Schedule",
  "machineID": "PERFLIN",
  "schemaVersion": "2",
  "results": {
    "netSdkVersion": "10.0.100-rc.2.25420.109",
    "aspNetCoreVersion": "10.0.0-rc.2.25420.109+619d5633513d",
    "netCoreAppVersion": "10.0.0-rc.2.25420.109+619d5633513d",
    "msbuild-version": "17.15.0.42205",
    "msbuild-display-version": "17.15.0.42205",
    "evaluation-time": 613.0,
    "evaluation-time-globbing": 6.0,
    "evaluation-time-pass0": 9.0,
    "evaluation-time-pass1": 340.0,
    "evaluation-time-pass2": 4.0,
    "evaluation-time-pass3": 70.1,
    "evaluation-time-pass3dot1": 78.2,
    "evaluation-time-pass4": 5.6,
    "evaluation-time-pass5": 103.8,
    "exit-code": 0.0,
    "build-time": 2493.66391,
    "info/test-asset": "Net8BlazorWasmApp",
    "info/test-scenario": "Rebuild",
    "info/msbuild-app": "Dotnet",
    "info/test-version": 1.0,
    "info/iterations-number": 10.0,
    "dotnet-version": "10.0.100-rc.2.25420.109"
  }
}
